README.md
setup.cfg
setup.py
gauss_bino_distribution/Binomialdistribution.py
gauss_bino_distribution/Gaussiandistribution.py
gauss_bino_distribution/Generaldistribution.py
gauss_bino_distribution/__init__.py
gauss_bino_distribution.egg-info/PKG-INFO
gauss_bino_distribution.egg-info/SOURCES.txt
gauss_bino_distribution.egg-info/dependency_links.txt
gauss_bino_distribution.egg-info/not-zip-safe
gauss_bino_distribution.egg-info/top_level.txt